fire_state/__init__.py
fire_state/state.py
fire_state-0.1.3.dist-info/LICENSE
fire_state-0.1.3.dist-info/WHEEL
fire_state-0.1.3.dist-info/METADATA
fire_state-0.1.3.dist-info/RECORD
