Metadata-Version: 2.1
Name: fire-state
Version: 0.1.3
Summary: Persist state across multiple pages in streamlit.
Author-email: Mr-Milk <yb97643@um.edu.mo>
Requires-Python: >=3.8
Classifier: License :: OSI Approved :: MIT License
Classifier: Programming Language :: Python :: 3
Classifier: Intended Audience :: Developers
Requires-Dist: streamlit
